now_2023/__init__.py
now_2023/data_generation/__init__.py
now_2023/data_generation/_cropped_hc_dataset.py
now_2023/data_generation/_toy_dataset.py
now_2023/data_generation/cli.py
now_2023/datasets/__init__.py
now_2023/datasets/_mri.py
now_2023/models/__init__.py
now_2023/models/_cnn.py
now_2023/models/_toy.py
now_2023/plotting/__init__.py
now_2023/plotting/_image.py
now_2023/utils/__init__.py
now_2023/utils/_images.py
now_2023/utils/_statistics.py
now_2023-0.1.3.dist-info/LICENSE
now_2023-0.1.3.dist-info/METADATA
now_2023-0.1.3.dist-info/WHEEL
now_2023-0.1.3.dist-info/RECORD
